{"_id":{"$oid":"61f3ff4ac11c5aed3015b869"},"timestamp":{"$date":"2022-01-29T14:36:54.285Z"},"author":{"$oid":"0000000a13d37dedfea5c730"},"comment_contents":"Chyba dla ciebie świnio!!!! zostawiłeś taki syf że pół dnia nie mogłem klopa doczyścić","__v":0}
{"_id":{"$oid":"61f3ff4ac91c5aed30eab839"},"timestamp":{"$date":"2022-01-28T14:35:54.285Z"},"author":{"$oid":"0000000bae7ab203a5ed2753"},"comment_contents":"Okropna toaleta, chyba ktoś tam umarł bo śmród jest taki że nawet po moim klocu nie było gorzej!","resource_uri":"/images/bad_toilet.jpg","__v":0}
{"_id":{"$oid":"61f3ff4ac11c5aed30eab869"},"timestamp":{"$date":"2022-01-29T14:35:54.285Z"},"author":{"$oid":"0000000bae7ab203a5ed2753"},"comment_contents":"bardzo przyjemne sranie weszło","__v":0}
{"_id":{"$oid":"61f3ff0050129b0207c8888f"},"timestamp":{"$date":"2022-01-28T14:34:40.582Z"},"author":{"$oid":"0000000a13d37dedfea5c730"},"comment_contents":"Okropny użytkownik, przez takich ludzi odechciewa się używać tego portalu!","__v":0}
{"_id":{"$oid":"61f3ff0050129b0207c8818f"},"timestamp":{"$date":"2022-01-28T14:34:40.582Z"},"author":{"$oid":"61fe7c3f57bfe76f5762a6b2"},"comment_contents":"Nie płacz tam tak bardzo kobieto, prawdziwy mężczyzna zawsze musi trochę nalać na podłogę hehe","__v":0}
